mod12_counter.v
// =======================================================
// TOP MODULE: Счетчик по модулю 12 с параллельным переносом
// =======================================================
module top (
    input wire clk,
    input wire reset_n,
    output wire [7:0] led,
    output wire [6:0] seg,
    output wire [1:0] digit,
    output wire spi_mosi,
    output wire spi_clk,
    output wire spi_cs
);

    wire reset = ~reset_n;
    wire [3:0] count;
    wire carry;

    counter12 counter_inst (
        .clk(clk),
        .reset(reset),
        .count(count),
        .carry(carry)
    );

    assign led = {4'b0, count};

    seg7_mux seg7_inst (
        .clk(clk),
        .reset(reset),
        .value(count),
        .seg(seg),
        .digit(digit)
    );

    spi_dac dac_inst (
        .clk(clk),
        .reset(reset),
        .data({4'b0, count}),
        .mosi(spi_mosi),
        .sclk(spi_clk),
        .cs(spi_cs)
    );

endmodule


// =======================================================
// СЧЕТЧИК ПО МОДУЛЮ 12 С ПАРАЛЛЕЛЬНЫМ ПЕРЕНОСОМ
// =======================================================
module counter12(
    input  wire clk,
    input  wire reset,
    output reg  [3:0] count,
    output wire carry
);

    wire [3:0] next_count = (count == 11) ? 4'd0 : count + 1;
    assign carry = (count == 11);

    always @(posedge clk or posedge reset) begin
        if (reset)
            count <= 4'd0;
        else
            count <= next_count;
    end
endmodule


// =======================================================
// МУЛЬТИПЛЕКСОР ДЛЯ 7-СЕГМЕНТНОГО ИНДИКАТОРА (2 РАЗРЯДА)
// =======================================================
module seg7_mux(
    input wire clk,
    input wire reset,
    input wire [3:0] value,
    output reg [6:0] seg,
    output reg [1:0] digit
);

    reg toggle;
    reg [3:0] digit_lo, digit_hi;
    wire [6:0] seg_lo, seg_hi;

    always @(*) begin
        digit_lo = value % 10;
        digit_hi = value / 10;
    end

    bcd_to_7seg bcd_lo (.bcd(digit_lo), .seg(seg_lo));
    bcd_to_7seg bcd_hi (.bcd(digit_hi), .seg(seg_hi));

    always @(posedge clk or posedge reset) begin
        if (reset)
            toggle <= 0;
        else
            toggle <= ~toggle;
    end

    always @(*) begin
        if (toggle) begin
            seg = seg_hi;
            digit = 2'b10;
        end else begin
            seg = seg_lo;
            digit = 2'b01;
        end
    end
endmodule


// =======================================================
// ПРЕОБРАЗОВАТЕЛЬ BCD -> 7-СЕГМЕНТНЫЙ КОД
// =======================================================
module bcd_to_7seg (
    input wire [3:0] bcd,
    output reg [6:0] seg
);
    always @(*) begin
        case (bcd)
            4'd0: seg = 7'b0111111; 
            4'd1: seg = 7'b0000110;
            4'd2: seg = 7'b1011011;
            4'd3: seg = 7'b1001111;
            4'd4: seg = 7'b1100110;
            4'd5: seg = 7'b1101101;
            4'd6: seg = 7'b1111101;
            4'd7: seg = 7'b0000111;
            4'd8: seg = 7'b1111111;
            4'd9: seg = 7'b1101111;
            default: seg = 7'b0000000;
        endcase
    end
endmodule


// =======================================================
// SPI-КОНТРОЛЛЕР ДЛЯ DAC (например, AD7302)
// =======================================================
module spi_dac (
    input wire clk,
    input wire reset,
    input wire [7:0] data,
    output reg mosi,
    output reg sclk,
    output reg cs
);
    reg [3:0] bit_cnt = 0;
    reg [7:0] shift_reg;
    reg [15:0] clk_div;
    localparam DIV = 50;

    parameter IDLE = 2'b00;
    parameter LOAD = 2'b01;
    parameter TRANSFER = 2'b10;

    reg [1:0] state;
    reg [1:0] next_state;

    always @(posedge clk or posedge reset) begin
        if (reset) begin
            state <= IDLE;
            clk_div <= 0;
            cs <= 1;
            sclk <= 0;
            mosi <= 0;
        end else begin
            clk_div <= clk_div + 1;
            if (clk_div == DIV) begin
                clk_div <= 0;
                case (state)
                    IDLE: begin
                        cs <= 1;
                        sclk <= 0;
                        next_state <= LOAD;
                    end
                    LOAD: begin
                        shift_reg <= data;
                        bit_cnt <= 7;
                        cs <= 0;
                        next_state <= TRANSFER;
                    end
                    TRANSFER: begin
                        mosi <= shift_reg[7];
                        shift_reg <= {shift_reg[6:0], 1'b0};
                        sclk <= ~sclk;
                        if (bit_cnt == 0)
                            next_state <= IDLE;
                        else
                            bit_cnt <= bit_cnt - 1;
                    end
                endcase
                state <= next_state;
            end
        end
    end
endmodule

testbench.v
`timescale 1 us / 100 ns

module testbench;

    // Тактовый и сброс
    reg clk = 1'b0;
    reg reset_n = 0;

    // Интерфейсы верхнего уровня
    wire [7:0] led;
    wire [6:0] seg;
    wire [1:0] digit;
    wire spi_mosi;
    wire spi_clk;
    wire spi_cs;

    // Генерация тактового сигнала (1 МГц)
    always #1 clk = ~clk; // Период 2 мкс → частота 500 кГц

    // Инстанцирование тестируемого модуля
    top dut (
        .clk(clk),
        .reset_n(reset_n),
        .led(led),
        .seg(seg),
        .digit(digit),
        .spi_mosi(spi_mosi),
        .spi_clk(spi_clk),
        .spi_cs(spi_cs)
    );

    initial begin
        $dumpfile("dump.vcd"); // <-- ОБЯЗАТЕЛЬНО
        $dumpvars(0, testbench); // Записываем все сигналы

        $display("Test started...");

        // Подаём сброс на старте
        reset_n = 0;
        #5;
        reset_n = 1;

        // Имитируем работу ~1000 тактов (примерно 2 мс)
        #2000;

        $display("Test finished.");
        $finish;
    end

endmodule

dump.vcd
$date
	Sat Apr 19 21:13:01 2025
$end
$version
	Icarus Verilog
$end
$timescale
	100ns
$end
$scope module testbench $end
$var wire 1 ! spi_mosi $end
$var wire 1 " spi_cs $end
$var wire 1 # spi_clk $end
$var wire 7 $ seg [6:0] $end
$var wire 8 % led [7:0] $end
$var wire 2 & digit [1:0] $end
$var reg 1 ' clk $end
$var reg 1 ( reset_n $end
$scope module dut $end
$var wire 1 ' clk $end
$var wire 1 ) reset $end
$var wire 1 ( reset_n $end
$var wire 1 ! spi_mosi $end
$var wire 1 " spi_cs $end
$var wire 1 # spi_clk $end
$var wire 7 * seg [6:0] $end
$var wire 8 + led [7:0] $end
$var wire 2 , digit [1:0] $end
$var wire 4 - count [3:0] $end
$var wire 1 . carry $end
$scope module counter_inst $end
$var wire 1 ' clk $end
$var wire 1 ) reset $end
$var wire 4 / next_count [3:0] $end
$var wire 1 . carry $end
$var reg 4 0 count [3:0] $end
$upscope $end
$scope module dac_inst $end
$var wire 1 ' clk $end
$var wire 8 1 data [7:0] $end
$var wire 1 ) reset $end
$var reg 4 2 bit_cnt [3:0] $end
$var reg 16 3 clk_div [15:0] $end
$var reg 1 " cs $end
$var reg 1 ! mosi $end
$var reg 2 4 next_state [1:0] $end
$var reg 1 # sclk $end
$var reg 8 5 shift_reg [7:0] $end
$var reg 2 6 state [1:0] $end
$upscope $end
$scope module seg7_inst $end
$var wire 1 ' clk $end
$var wire 1 ) reset $end
$var wire 4 7 value [3:0] $end
$var wire 7 8 seg_lo [6:0] $end
$var wire 7 9 seg_hi [6:0] $end
$var reg 2 : digit [1:0] $end
$var reg 4 ; digit_hi [3:0] $end
$var reg 4 < digit_lo [3:0] $end
$var reg 7 = seg [6:0] $end
$var reg 1 > toggle $end
$scope module bcd_hi $end
$var wire 4 ? bcd [3:0] $end
$var reg 7 @ seg [6:0] $end
$upscope $end
$scope module bcd_lo $end
$var wire 4 A bcd [3:0] $end
$var reg 7 B seg [6:0] $end
$upscope $end
$upscope $end
$upscope $end
$upscope $end
$enddefinitions $end
#0
$dumpvars
b111111 B
b0 A
b111111 @
b0 ?
0>
b111111 =
b0 <
b0 ;
b1 :
b111111 9
b111111 8
b0 7
b0 6
bx 5
bx 4
b0 3
b0 2
b0 1
b0 0
b1 /
0.
b0 -
b1 ,
b0 +
b111111 *
1)
0(
0'
b1 &
b0 %
b111111 $
0#
1"
0!
$end
#10
1'
#20
0'
#30
1'
#40
0'
#50
b110 8
b110 B
b10 &
b10 ,
b10 :
b10 /
b1 <
b1 A
b1 3
1>
b1 1
b1 %
b1 +
b1 -
b1 0
b1 7
0)
1'
1(
#60
0'
#70
b1011011 8
b1011011 B
b11 /
b10 <
b10 A
b1 &
b1 ,
b1 :
b1011011 $
b1011011 *
b1011011 =
b10 1
b10 %
b10 +
b10 -
b10 0
b10 7
0>
b10 3
1'
#80
0'
#90
b1001111 8
b1001111 B
b10 &
b10 ,
b10 :
b111111 $
b111111 *
b111111 =
b100 /
b11 <
b11 A
b11 3
1>
b11 1
b11 %
b11 +
b11 -
b11 0
b11 7
1'
#100
0'
#110
b1100110 8
b1100110 B
b101 /
b100 <
b100 A
b1 &
b1 ,
b1 :
b1100110 $
b1100110 *
b1100110 =
b100 1
b100 %
b100 +
b100 -
b100 0
b100 7
0>
b100 3
1'
#120
0'
#130
b1101101 8
b1101101 B
b10 &
b10 ,
b10 :
b111111 $
b111111 *
b111111 =
b110 /
b101 <
b101 A
b101 3
1>
b101 1
b101 %
b101 +
b101 -
b101 0
b101 7
1'
#140
0'
#150
b1111101 8
b1111101 B
b111 /
b110 <
b110 A
b1 &
b1 ,
b1 :
b1111101 $
b1111101 *
b1111101 =
b110 1
b110 %
b110 +
b110 -
b110 0
b110 7
0>
b110 3
1'
#160
0'
#170
b111 8
b111 B
b10 &
b10 ,
b10 :
b111111 $
b111111 *
b111111 =
b1000 /
b111 <
b111 A
b111 3
1>
b111 1
b111 %
b111 +
b111 -
b111 0
b111 7
1'
#180
0'
#190
b1111111 8
b1111111 B
b1001 /
b1000 <
b1000 A
b1 &
b1 ,
b1 :
b1111111 $
b1111111 *
b1111111 =
b1000 1
b1000 %
b1000 +
b1000 -
b1000 0
b1000 7
0>
b1000 3
1'
#200
0'
#210
b1101111 8
b1101111 B
b10 &
b10 ,
b10 :
b111111 $
b111111 *
b111111 =
b1010 /
b1001 <
b1001 A
b1001 3
1>
b1001 1
b1001 %
b1001 +
b1001 -
b1001 0
b1001 7
1'
#220
0'
#230
b110 9
b110 @
b111111 8
b111111 B
b1011 /
b1 ;
b1 ?
b0 <
b0 A
b1 &
b1 ,
b1 :
b111111 $
b111111 *
b111111 =
b1010 1
b1010 %
b1010 +
b1010 -
b1010 0
b1010 7
0>
b1010 3
1'
#240
0'
#250
b110 8
b110 B
b10 &
b10 ,
b10 :
b110 $
b110 *
b110 =
b0 /
b1 <
b1 A
b1011 3
1>
1.
b1011 1
b1011 %
b1011 +
b1011 -
b1011 0
b1011 7
1'
#260
0'
#270
b111111 $
b111111 *
b111111 =
b111111 9
b111111 @
b111111 8
b111111 B
b1 /
b0 ;
b0 ?
b0 <
b0 A
b1 &
b1 ,
b1 :
0.
b0 1
b0 %
b0 +
b0 -
b0 0
b0 7
0>
b1100 3
1'
#280
0'
#290
b110 8
b110 B
b10 &
b10 ,
b10 :
b10 /
b1 <
b1 A
b1101 3
1>
b1 1
b1 %
b1 +
b1 -
b1 0
b1 7
1'
#300
0'
#310
b1011011 8
b1011011 B
b11 /
b10 <
b10 A
b1 &
b1 ,
b1 :
b1011011 $
b1011011 *
b1011011 =
b10 1
b10 %
b10 +
b10 -
b10 0
b10 7
0>
b1110 3
1'
#320
0'
#330
b1001111 8
b1001111 B
b10 &
b10 ,
b10 :
b111111 $
b111111 *
b111111 =
b100 /
b11 <
b11 A
b1111 3
1>
b11 1
b11 %
b11 +
b11 -
b11 0
b11 7
1'
#340
0'
#350
b1100110 8
b1100110 B
b101 /
b100 <
b100 A
b1 &
b1 ,
b1 :
b1100110 $
b1100110 *
b1100110 =
b100 1
b100 %
b100 +
b100 -
b100 0
b100 7
0>
b10000 3
1'
#360
0'
#370
b1101101 8
b1101101 B
b10 &
b10 ,
b10 :
b111111 $
b111111 *
b111111 =
b110 /
b101 <
b101 A
b10001 3
1>
b101 1
b101 %
b101 +
b101 -
b101 0
b101 7
1'
#380
0'
#390
b1111101 8
b1111101 B
b111 /
b110 <
b110 A
b1 &
b1 ,
b1 :
b1111101 $
b1111101 *
b1111101 =
b110 1
b110 %
b110 +
b110 -
b110 0
b110 7
0>
b10010 3
1'
#400
0'
#410
b111 8
b111 B
b10 &
b10 ,
b10 :
b111111 $
b111111 *
b111111 =
b1000 /
b111 <
b111 A
b10011 3
1>
b111 1
b111 %
b111 +
b111 -
b111 0
b111 7
1'
#420
0'
#430
b1111111 8
b1111111 B
b1001 /
b1000 <
b1000 A
b1 &
b1 ,
b1 :
b1111111 $
b1111111 *
b1111111 =
b1000 1
b1000 %
b1000 +
b1000 -
b1000 0
b1000 7
0>
b10100 3
1'
#440
0'
#450
b1101111 8
b1101111 B
b10 &
b10 ,
b10 :
b111111 $
b111111 *
b111111 =
b1010 /
b1001 <
b1001 A
b10101 3
1>
b1001 1
b1001 %
b1001 +
b1001 -
b1001 0
b1001 7
1'
#460
0'
#470
b110 9
b110 @
b111111 8
b111111 B
b1011 /
b1 ;
b1 ?
b0 <
b0 A
b1 &
b1 ,
b1 :
b111111 $
b111111 *
b111111 =
b1010 1
b1010 %
b1010 +
b1010 -
b1010 0
b1010 7
0>
b10110 3
1'
#480
0'
#490
b110 8
b110 B
b10 &
b10 ,
b10 :
b110 $
b110 *
b110 =
b0 /
b1 <
b1 A
b10111 3
1>
1.
b1011 1
b1011 %
b1011 +
b1011 -
b1011 0
b1011 7
1'
#500
0'
#510
b111111 $
b111111 *
b111111 =
b111111 9
b111111 @
b111111 8
b111111 B
b1 /
b0 ;
b0 ?
b0 <
b0 A
b1 &
b1 ,
b1 :
0.
b0 1
b0 %
b0 +
b0 -
b0 0
b0 7
0>
b11000 3
1'
#520
0'
#530
b110 8
b110 B
b10 &
b10 ,
b10 :
b10 /
b1 <
b1 A
b11001 3
1>
b1 1
b1 %
b1 +
b1 -
b1 0
b1 7
1'
#540
0'
#550
b1011011 8
b1011011 B
b11 /
b10 <
b10 A
b1 &
b1 ,
b1 :
b1011011 $
b1011011 *
b1011011 =
b10 1
b10 %
b10 +
b10 -
b10 0
b10 7
0>
b11010 3
1'
#560
0'
#570
b1001111 8
b1001111 B
b10 &
b10 ,
b10 :
b111111 $
b111111 *
b111111 =
b100 /
b11 <
b11 A
b11011 3
1>
b11 1
b11 %
b11 +
b11 -
b11 0
b11 7
1'
#580
0'
#590
b1100110 8
b1100110 B
b101 /
b100 <
b100 A
b1 &
b1 ,
b1 :
b1100110 $
b1100110 *
b1100110 =
b100 1
b100 %
b100 +
b100 -
b100 0
b100 7
0>
b11100 3
1'
#600
0'
#610
b1101101 8
b1101101 B
b10 &
b10 ,
b10 :
b111111 $
b111111 *
b111111 =
b110 /
b101 <
b101 A
b11101 3
1>
b101 1
b101 %
b101 +
b101 -
b101 0
b101 7
1'
#620
0'
#630
b1111101 8
b1111101 B
b111 /
b110 <
b110 A
b1 &
b1 ,
b1 :
b1111101 $
b1111101 *
b1111101 =
b110 1
b110 %
b110 +
b110 -
b110 0
b110 7
0>
b11110 3
1'
#640
0'
#650
b111 8
b111 B
b10 &
b10 ,
b10 :
b111111 $
b111111 *
b111111 =
b1000 /
b111 <
b111 A
b11111 3
1>
b111 1
b111 %
b111 +
b111 -
b111 0
b111 7
1'
#660
0'
#670
b1111111 8
b1111111 B
b1001 /
b1000 <
b1000 A
b1 &
b1 ,
b1 :
b1111111 $
b1111111 *
b1111111 =
b1000 1
b1000 %
b1000 +
b1000 -
b1000 0
b1000 7
0>
b100000 3
1'
#680
0'
#690
b1101111 8
b1101111 B
b10 &
b10 ,
b10 :
b111111 $
b111111 *
b111111 =
b1010 /
b1001 <
b1001 A
b100001 3
1>
b1001 1
b1001 %
b1001 +
b1001 -
b1001 0
b1001 7
1'
#700
0'
#710
b110 9
b110 @
b111111 8
b111111 B
b1011 /
b1 ;
b1 ?
b0 <
b0 A
b1 &
b1 ,
b1 :
b111111 $
b111111 *
b111111 =
b1010 1
b1010 %
b1010 +
b1010 -
b1010 0
b1010 7
0>
b100010 3
1'
#720
0'
#730
b110 8
b110 B
b10 &
b10 ,
b10 :
b110 $
b110 *
b110 =
b0 /
b1 <
b1 A
b100011 3
1>
1.
b1011 1
b1011 %
b1011 +
b1011 -
b1011 0
b1011 7
1'
#740
0'
#750
b111111 $
b111111 *
b111111 =
b111111 9
b111111 @
b111111 8
b111111 B
b1 /
b0 ;
b0 ?
b0 <
b0 A
b1 &
b1 ,
b1 :
0.
b0 1
b0 %
b0 +
b0 -
b0 0
b0 7
0>
b100100 3
1'
#760
0'
#770
b110 8
b110 B
b10 &
b10 ,
b10 :
b10 /
b1 <
b1 A
b100101 3
1>
b1 1
b1 %
b1 +
b1 -
b1 0
b1 7
1'
#780
0'
#790
b1011011 8
b1011011 B
b11 /
b10 <
b10 A
b1 &
b1 ,
b1 :
b1011011 $
b1011011 *
b1011011 =
b10 1
b10 %
b10 +
b10 -
b10 0
b10 7
0>
b100110 3
1'
#800
0'
#810
b1001111 8
b1001111 B
b10 &
b10 ,
b10 :
b111111 $
b111111 *
b111111 =
b100 /
b11 <
b11 A
b100111 3
1>
b11 1
b11 %
b11 +
b11 -
b11 0
b11 7
1'
#820
0'
#830
b1100110 8
b1100110 B
b101 /
b100 <
b100 A
b1 &
b1 ,
b1 :
b1100110 $
b1100110 *
b1100110 =
b100 1
b100 %
b100 +
b100 -
b100 0
b100 7
0>
b101000 3
1'
#840
0'
#850
b1101101 8
b1101101 B
b10 &
b10 ,
b10 :
b111111 $
b111111 *
b111111 =
b110 /
b101 <
b101 A
b101001 3
1>
b101 1
b101 %
b101 +
b101 -
b101 0
b101 7
1'
#860
0'
#870
b1111101 8
b1111101 B
b111 /
b110 <
b110 A
b1 &
b1 ,
b1 :
b1111101 $
b1111101 *
b1111101 =
b110 1
b110 %
b110 +
b110 -
b110 0
b110 7
0>
b101010 3
1'
#880
0'
#890
b111 8
b111 B
b10 &
b10 ,
b10 :
b111111 $
b111111 *
b111111 =
b1000 /
b111 <
b111 A
b101011 3
1>
b111 1
b111 %
b111 +
b111 -
b111 0
b111 7
1'
#900
0'
#910
b1111111 8
b1111111 B
b1001 /
b1000 <
b1000 A
b1 &
b1 ,
b1 :
b1111111 $
b1111111 *
b1111111 =
b1000 1
b1000 %
b1000 +
b1000 -
b1000 0
b1000 7
0>
b101100 3
1'
#920
0'
#930
b1101111 8
b1101111 B
b10 &
b10 ,
b10 :
b111111 $
b111111 *
b111111 =
b1010 /
b1001 <
b1001 A
b101101 3
1>
b1001 1
b1001 %
b1001 +
b1001 -
b1001 0
b1001 7
1'
#940
0'
#950
b110 9
b110 @
b111111 8
b111111 B
b1011 /
b1 ;
b1 ?
b0 <
b0 A
b1 &
b1 ,
b1 :
b111111 $
b111111 *
b111111 =
b1010 1
b1010 %
b1010 +
b1010 -
b1010 0
b1010 7
0>
b101110 3
1'
#960
0'
#970
b110 8
b110 B
b10 &
b10 ,
b10 :
b110 $
b110 *
b110 =
b0 /
b1 <
b1 A
b101111 3
1>
1.
b1011 1
b1011 %
b1011 +
b1011 -
b1011 0
b1011 7
1'
#980
0'
#990
b111111 $
b111111 *
b111111 =
b111111 9
b111111 @
b111111 8
b111111 B
b1 /
b0 ;
b0 ?
b0 <
b0 A
b1 &
b1 ,
b1 :
0.
b0 1
b0 %
b0 +
b0 -
b0 0
b0 7
0>
b110000 3
1'
#1000
0'
#1010
b110 8
b110 B
b10 &
b10 ,
b10 :
b10 /
b1 <
b1 A
b110001 3
1>
b1 1
b1 %
b1 +
b1 -
b1 0
b1 7
1'
#1020
0'
#1030
b1011011 8
b1011011 B
b11 /
b10 <
b10 A
b1 &
b1 ,
b1 :
b1011011 $
b1011011 *
b1011011 =
b10 1
b10 %
b10 +
b10 -
b10 0
b10 7
0>
b110010 3
1'
#1040
0'
#1050
b1001111 8
b1001111 B
b10 &
b10 ,
b10 :
b111111 $
b111111 *
b111111 =
b100 /
b11 <
b11 A
bx 6
b1 4
b0 3
1>
b11 1
b11 %
b11 +
b11 -
b11 0
b11 7
1'
#1060
0'
#1070
b1100110 8
b1100110 B
b101 /
b100 <
b100 A
b1 &
b1 ,
b1 :
b1100110 $
b1100110 *
b1100110 =
b100 1
b100 %
b100 +
b100 -
b100 0
b100 7
0>
b1 3
1'
#1080
0'
#1090
b1101101 8
b1101101 B
b10 &
b10 ,
b10 :
b111111 $
b111111 *
b111111 =
b110 /
b101 <
b101 A
b10 3
1>
b101 1
b101 %
b101 +
b101 -
b101 0
b101 7
1'
#1100
0'
#1110
b1111101 8
b1111101 B
b111 /
b110 <
b110 A
b1 &
b1 ,
b1 :
b1111101 $
b1111101 *
b1111101 =
b110 1
b110 %
b110 +
b110 -
b110 0
b110 7
0>
b11 3
1'
#1120
0'
#1130
b111 8
b111 B
b10 &
b10 ,
b10 :
b111111 $
b111111 *
b111111 =
b1000 /
b111 <
b111 A
b100 3
1>
b111 1
b111 %
b111 +
b111 -
b111 0
b111 7
1'
#1140
0'
#1150
b1111111 8
b1111111 B
b1001 /
b1000 <
b1000 A
b1 &
b1 ,
b1 :
b1111111 $
b1111111 *
b1111111 =
b1000 1
b1000 %
b1000 +
b1000 -
b1000 0
b1000 7
0>
b101 3
1'
#1160
0'
#1170
b1101111 8
b1101111 B
b10 &
b10 ,
b10 :
b111111 $
b111111 *
b111111 =
b1010 /
b1001 <
b1001 A
b110 3
1>
b1001 1
b1001 %
b1001 +
b1001 -
b1001 0
b1001 7
1'
#1180
0'
#1190
b110 9
b110 @
b111111 8
b111111 B
b1011 /
b1 ;
b1 ?
b0 <
b0 A
b1 &
b1 ,
b1 :
b111111 $
b111111 *
b111111 =
b1010 1
b1010 %
b1010 +
b1010 -
b1010 0
b1010 7
0>
b111 3
1'
#1200
0'
#1210
b110 8
b110 B
b10 &
b10 ,
b10 :
b110 $
b110 *
b110 =
b0 /
b1 <
b1 A
b1000 3
1>
1.
b1011 1
b1011 %
b1011 +
b1011 -
b1011 0
b1011 7
1'
#1220
0'
#1230
b111111 $
b111111 *
b111111 =
b111111 9
b111111 @
b111111 8
b111111 B
b1 /
b0 ;
b0 ?
b0 <
b0 A
b1 &
b1 ,
b1 :
0.
b0 1
b0 %
b0 +
b0 -
b0 0
b0 7
0>
b1001 3
1'
#1240
0'
#1250
b110 8
b110 B
b10 &
b10 ,
b10 :
b10 /
b1 <
b1 A
b1010 3
1>
b1 1
b1 %
b1 +
b1 -
b1 0
b1 7
1'
#1260
0'
#1270
b1011011 8
b1011011 B
b11 /
b10 <
b10 A
b1 &
b1 ,
b1 :
b1011011 $
b1011011 *
b1011011 =
b10 1
b10 %
b10 +
b10 -
b10 0
b10 7
0>
b1011 3
1'
#1280
0'
#1290
b1001111 8
b1001111 B
b10 &
b10 ,
b10 :
b111111 $
b111111 *
b111111 =
b100 /
b11 <
b11 A
b1100 3
1>
b11 1
b11 %
b11 +
b11 -
b11 0
b11 7
1'
#1300
0'
#1310
b1100110 8
b1100110 B
b101 /
b100 <
b100 A
b1 &
b1 ,
b1 :
b1100110 $
b1100110 *
b1100110 =
b100 1
b100 %
b100 +
b100 -
b100 0
b100 7
0>
b1101 3
1'
#1320
0'
#1330
b1101101 8
b1101101 B
b10 &
b10 ,
b10 :
b111111 $
b111111 *
b111111 =
b110 /
b101 <
b101 A
b1110 3
1>
b101 1
b101 %
b101 +
b101 -
b101 0
b101 7
1'
#1340
0'
#1350
b1111101 8
b1111101 B
b111 /
b110 <
b110 A
b1 &
b1 ,
b1 :
b1111101 $
b1111101 *
b1111101 =
b110 1
b110 %
b110 +
b110 -
b110 0
b110 7
0>
b1111 3
1'
#1360
0'
#1370
b111 8
b111 B
b10 &
b10 ,
b10 :
b111111 $
b111111 *
b111111 =
b1000 /
b111 <
b111 A
b10000 3
1>
b111 1
b111 %
b111 +
b111 -
b111 0
b111 7
1'
#1380
0'
#1390
b1111111 8
b1111111 B
b1001 /
b1000 <
b1000 A
b1 &
b1 ,
b1 :
b1111111 $
b1111111 *
b1111111 =
b1000 1
b1000 %
b1000 +
b1000 -
b1000 0
b1000 7
0>
b10001 3
1'
#1400
0'
#1410
b1101111 8
b1101111 B
b10 &
b10 ,
b10 :
b111111 $
b111111 *
b111111 =
b1010 /
b1001 <
b1001 A
b10010 3
1>
b1001 1
b1001 %
b1001 +
b1001 -
b1001 0
b1001 7
1'
#1420
0'
#1430
b110 9
b110 @
b111111 8
b111111 B
b1011 /
b1 ;
b1 ?
b0 <
b0 A
b1 &
b1 ,
b1 :
b111111 $
b111111 *
b111111 =
b1010 1
b1010 %
b1010 +
b1010 -
b1010 0
b1010 7
0>
b10011 3
1'
#1440
0'
#1450
b110 8
b110 B
b10 &
b10 ,
b10 :
b110 $
b110 *
b110 =
b0 /
b1 <
b1 A
b10100 3
1>
1.
b1011 1
b1011 %
b1011 +
b1011 -
b1011 0
b1011 7
1'
#1460
0'
#1470
b111111 $
b111111 *
b111111 =
b111111 9
b111111 @
b111111 8
b111111 B
b1 /
b0 ;
b0 ?
b0 <
b0 A
b1 &
b1 ,
b1 :
0.
b0 1
b0 %
b0 +
b0 -
b0 0
b0 7
0>
b10101 3
1'
#1480
0'
#1490
b110 8
b110 B
b10 &
b10 ,
b10 :
b10 /
b1 <
b1 A
b10110 3
1>
b1 1
b1 %
b1 +
b1 -
b1 0
b1 7
1'
#1500
0'
#1510
b1011011 8
b1011011 B
b11 /
b10 <
b10 A
b1 &
b1 ,
b1 :
b1011011 $
b1011011 *
b1011011 =
b10 1
b10 %
b10 +
b10 -
b10 0
b10 7
0>
b10111 3
1'
#1520
0'
#1530
b1001111 8
b1001111 B
b10 &
b10 ,
b10 :
b111111 $
b111111 *
b111111 =
b100 /
b11 <
b11 A
b11000 3
1>
b11 1
b11 %
b11 +
b11 -
b11 0
b11 7
1'
#1540
0'
#1550
b1100110 8
b1100110 B
b101 /
b100 <
b100 A
b1 &
b1 ,
b1 :
b1100110 $
b1100110 *
b1100110 =
b100 1
b100 %
b100 +
b100 -
b100 0
b100 7
0>
b11001 3
1'
#1560
0'
#1570
b1101101 8
b1101101 B
b10 &
b10 ,
b10 :
b111111 $
b111111 *
b111111 =
b110 /
b101 <
b101 A
b11010 3
1>
b101 1
b101 %
b101 +
b101 -
b101 0
b101 7
1'
#1580
0'
#1590
b1111101 8
b1111101 B
b111 /
b110 <
b110 A
b1 &
b1 ,
b1 :
b1111101 $
b1111101 *
b1111101 =
b110 1
b110 %
b110 +
b110 -
b110 0
b110 7
0>
b11011 3
1'
#1600
0'
#1610
b111 8
b111 B
b10 &
b10 ,
b10 :
b111111 $
b111111 *
b111111 =
b1000 /
b111 <
b111 A
b11100 3
1>
b111 1
b111 %
b111 +
b111 -
b111 0
b111 7
1'
#1620
0'
#1630
b1111111 8
b1111111 B
b1001 /
b1000 <
b1000 A
b1 &
b1 ,
b1 :
b1111111 $
b1111111 *
b1111111 =
b1000 1
b1000 %
b1000 +
b1000 -
b1000 0
b1000 7
0>
b11101 3
1'
#1640
0'
#1650
b1101111 8
b1101111 B
b10 &
b10 ,
b10 :
b111111 $
b111111 *
b111111 =
b1010 /
b1001 <
b1001 A
b11110 3
1>
b1001 1
b1001 %
b1001 +
b1001 -
b1001 0
b1001 7
1'
#1660
0'
#1670
b110 9
b110 @
b111111 8
b111111 B
b1011 /
b1 ;
b1 ?
b0 <
b0 A
b1 &
b1 ,
b1 :
b111111 $
b111111 *
b111111 =
b1010 1
b1010 %
b1010 +
b1010 -
b1010 0
b1010 7
0>
b11111 3
1'
#1680
0'
#1690
b110 8
b110 B
b10 &
b10 ,
b10 :
b110 $
b110 *
b110 =
b0 /
b1 <
b1 A
b100000 3
1>
1.
b1011 1
b1011 %
b1011 +
b1011 -
b1011 0
b1011 7
1'
#1700
0'
#1710
b111111 $
b111111 *
b111111 =
b111111 9
b111111 @
b111111 8
b111111 B
b1 /
b0 ;
b0 ?
b0 <
b0 A
b1 &
b1 ,
b1 :
0.
b0 1
b0 %
b0 +
b0 -
b0 0
b0 7
0>
b100001 3
1'
#1720
0'
#1730
b110 8
b110 B
b10 &
b10 ,
b10 :
b10 /
b1 <
b1 A
b100010 3
1>
b1 1
b1 %
b1 +
b1 -
b1 0
b1 7
1'
#1740
0'
#1750
b1011011 8
b1011011 B
b11 /
b10 <
b10 A
b1 &
b1 ,
b1 :
b1011011 $
b1011011 *
b1011011 =
b10 1
b10 %
b10 +
b10 -
b10 0
b10 7
0>
b100011 3
1'
#1760
0'
#1770
b1001111 8
b1001111 B
b10 &
b10 ,
b10 :
b111111 $
b111111 *
b111111 =
b100 /
b11 <
b11 A
b100100 3
1>
b11 1
b11 %
b11 +
b11 -
b11 0
b11 7
1'
#1780
0'
#1790
b1100110 8
b1100110 B
b101 /
b100 <
b100 A
b1 &
b1 ,
b1 :
b1100110 $
b1100110 *
b1100110 =
b100 1
b100 %
b100 +
b100 -
b100 0
b100 7
0>
b100101 3
1'
#1800
0'
#1810
b1101101 8
b1101101 B
b10 &
b10 ,
b10 :
b111111 $
b111111 *
b111111 =
b110 /
b101 <
b101 A
b100110 3
1>
b101 1
b101 %
b101 +
b101 -
b101 0
b101 7
1'
#1820
0'
#1830
b1111101 8
b1111101 B
b111 /
b110 <
b110 A
b1 &
b1 ,
b1 :
b1111101 $
b1111101 *
b1111101 =
b110 1
b110 %
b110 +
b110 -
b110 0
b110 7
0>
b100111 3
1'
#1840
0'
#1850
b111 8
b111 B
b10 &
b10 ,
b10 :
b111111 $
b111111 *
b111111 =
b1000 /
b111 <
b111 A
b101000 3
1>
b111 1
b111 %
b111 +
b111 -
b111 0
b111 7
1'
#1860
0'
#1870
b1111111 8
b1111111 B
b1001 /
b1000 <
b1000 A
b1 &
b1 ,
b1 :
b1111111 $
b1111111 *
b1111111 =
b1000 1
b1000 %
b1000 +
b1000 -
b1000 0
b1000 7
0>
b101001 3
1'
#1880
0'
#1890
b1101111 8
b1101111 B
b10 &
b10 ,
b10 :
b111111 $
b111111 *
b111111 =
b1010 /
b1001 <
b1001 A
b101010 3
1>
b1001 1
b1001 %
b1001 +
b1001 -
b1001 0
b1001 7
1'
#1900
0'
