mod12_counter.v
// =======================================================
// TOP MODULE: Счетчик по модулю 12 с параллельным переносом, 
// с индикацией состояние светодиодами, 
// 7-сегментным индикатором и цифроаналоговым преобразователем.
// =======================================================
module top (
    input wire clk,
    input wire reset_n,
    output wire [7:0] led,
    output wire [6:0] lseg,
    output wire [6:0] hseg,
    output wire [7:0] do
);

    wire reset = ~reset_n;
    wire [3:0] count;
    wire carry;

    counter12 counter_inst (
        .clk(clk),
        .reset(reset),
        .count(count),
        .carry(carry)
    );

    assign led = {4'b0, count};

    assign do = count; // DAC

    seg7 seg7_inst (
        .clk(clk),
        .reset(reset),
        .value(count),
        .lseg(lseg),
        .hseg(hseg)
    );

endmodule


// =======================================================
// СЧЕТЧИК ПО МОДУЛЮ 12 С ПАРАЛЛЕЛЬНЫМ ПЕРЕНОСОМ
// =======================================================
module counter12(
    input  wire clk,
    input  wire reset,
    output reg  [3:0] count,
    output wire carry
);

    wire [3:0] next_count = (count == 11) ? 4'd0 : count + 1;
    assign carry = (count == 11);

    always @(posedge clk or posedge reset) begin
        if (reset)
            count <= 4'd0;
        else
            count <= next_count;
    end
endmodule


// =======================================================
// 7-СЕГМЕНТНЫЙ ИНДИКАТОР (2 РАЗРЯДА)
// =======================================================
module seg7(
    input wire clk,
    input wire reset,
    input wire [3:0] value,
    output reg [6:0] lseg,
    output reg [6:0] hseg
);

    reg [3:0] ones, tens;

    always @(*) begin
        ones = value % 10;
        tens = value / 10;

        case (ones)                     // hex       maybe (invert)
            4'd0: lseg = 7'b1000000;    // 40            011 1111
            4'd1: lseg = 7'b1111001;    // 79            000 0110
            4'd2: lseg = 7'b0100100;    // 24            101 1011
            4'd3: lseg = 7'b0110000;    // 30            100 1111
            4'd4: lseg = 7'b0011001;    // 19            110 0110
            4'd5: lseg = 7'b0010010;    // 12            110 1101
            4'd6: lseg = 7'b0000010;    // 02            111 1101
            4'd7: lseg = 7'b1111000;    // 78            000 0111
            4'd8: lseg = 7'b0000000;    // 00            111 1111
            4'd9: lseg = 7'b0010000;    // 10            110 1111
            default: lseg = 7'b1111111; // 7F            000 0000
        endcase

        case (tens)
            4'd0: hseg = 7'b1000000;    //               011 1111
            4'd1: hseg = 7'b1111001;    //               000 0110
            default: hseg = 7'b1111111; //               000 0000
        endcase
    end
endmodule

testbench.v
`timescale 1 us / 100 ns

module testbench;

    // Тактовый и сброс
    reg clk = 1'b0;
    reg reset_n = 0;

    // Интерфейсы верхнего уровня
    wire [7:0] led;
    wire [6:0] lseg;
    wire [6:0] hseg;
    wire [7:0] do;

    // Генерация тактового сигнала (1 МГц)
    always #1 clk = ~clk; // Период 2 мкс → частота 500 кГц

    // Инстанцирование тестируемого модуля
    top dut (
        .clk(clk),
        .reset_n(reset_n),
        .led(led),
        .lseg(lseg),
        .hseg(hseg),
        .do(do)
    );

    initial begin
        $dumpfile("dump.vcd"); 
        $dumpvars(0, testbench); // Записываем все сигналы

        $display("Test started...");

        // Подаём сброс на старте
        reset_n = 0;
        #5;
        reset_n = 1;

        // Имитируем работу ~1000 тактов 
        #2000;

        $display("Test finished.");
        $finish;
    end

endmodule

dump.vcd
$date
	Sun Apr 20 00:17:51 2025
$end
$version
	Icarus Verilog
$end
$timescale
	100ns
$end
$scope module testbench $end
$var wire 7 ! lseg [6:0] $end
$var wire 8 " led [7:0] $end
$var wire 7 # hseg [6:0] $end
$var wire 8 $ do [7:0] $end
$var reg 1 % clk $end
$var reg 1 & reset_n $end
$scope module dut $end
$var wire 1 % clk $end
$var wire 1 ' reset $end
$var wire 1 & reset_n $end
$var wire 7 ( lseg [6:0] $end
$var wire 8 ) led [7:0] $end
$var wire 7 * hseg [6:0] $end
$var wire 8 + do [7:0] $end
$var wire 4 , count [3:0] $end
$var wire 1 - carry $end
$scope module counter_inst $end
$var wire 1 % clk $end
$var wire 1 ' reset $end
$var wire 4 . next_count [3:0] $end
$var wire 1 - carry $end
$var reg 4 / count [3:0] $end
$upscope $end
$scope module seg7_inst $end
$var wire 1 % clk $end
$var wire 1 ' reset $end
$var wire 4 0 value [3:0] $end
$var reg 7 1 hseg [6:0] $end
$var reg 7 2 lseg [6:0] $end
$var reg 4 3 ones [3:0] $end
$var reg 4 4 tens [3:0] $end
$upscope $end
$upscope $end
$upscope $end
$enddefinitions $end
#0
$dumpvars
b0 4
b0 3
b1000000 2
b1000000 1
b0 0
b0 /
b1 .
0-
b0 ,
b0 +
b1000000 *
b0 )
b1000000 (
1'
0&
0%
b0 $
b1000000 #
b0 "
b1000000 !
$end
#10
1%
#20
0%
#30
1%
#40
0%
#50
b10 .
b1111001 !
b1111001 (
b1111001 2
b1 3
b1 $
b1 +
b1 "
b1 )
b1 ,
b1 /
b1 0
0'
1%
1&
#60
0%
#70
b11 .
b100100 !
b100100 (
b100100 2
b10 3
b10 $
b10 +
b10 "
b10 )
b10 ,
b10 /
b10 0
1%
#80
0%
#90
b100 .
b110000 !
b110000 (
b110000 2
b11 3
b11 $
b11 +
b11 "
b11 )
b11 ,
b11 /
b11 0
1%
#100
0%
#110
b101 .
b11001 !
b11001 (
b11001 2
b100 3
b100 $
b100 +
b100 "
b100 )
b100 ,
b100 /
b100 0
1%
#120
0%
#130
b110 .
b10010 !
b10010 (
b10010 2
b101 3
b101 $
b101 +
b101 "
b101 )
b101 ,
b101 /
b101 0
1%
#140
0%
#150
b111 .
b10 !
b10 (
b10 2
b110 3
b110 $
b110 +
b110 "
b110 )
b110 ,
b110 /
b110 0
1%
#160
0%
#170
b1000 .
b1111000 !
b1111000 (
b1111000 2
b111 3
b111 $
b111 +
b111 "
b111 )
b111 ,
b111 /
b111 0
1%
#180
0%
#190
b1001 .
b0 !
b0 (
b0 2
b1000 3
b1000 $
b1000 +
b1000 "
b1000 )
b1000 ,
b1000 /
b1000 0
1%
#200
0%
#210
b1010 .
b10000 !
b10000 (
b10000 2
b1001 3
b1001 $
b1001 +
b1001 "
b1001 )
b1001 ,
b1001 /
b1001 0
1%
#220
0%
#230
b1011 .
b1111001 #
b1111001 *
b1111001 1
b1000000 !
b1000000 (
b1000000 2
b1 4
b0 3
b1010 $
b1010 +
b1010 "
b1010 )
b1010 ,
b1010 /
b1010 0
1%
#240
0%
#250
b0 .
b1111001 !
b1111001 (
b1111001 2
b1 3
1-
b1011 $
b1011 +
b1011 "
b1011 )
b1011 ,
b1011 /
b1011 0
1%
#260
0%
#270
b1 .
b1000000 #
b1000000 *
b1000000 1
b1000000 !
b1000000 (
b1000000 2
b0 4
b0 3
0-
b0 $
b0 +
b0 "
b0 )
b0 ,
b0 /
b0 0
1%
#280
0%
#290
b10 .
b1111001 !
b1111001 (
b1111001 2
b1 3
b1 $
b1 +
b1 "
b1 )
b1 ,
b1 /
b1 0
1%
#300
0%
#310
b11 .
b100100 !
b100100 (
b100100 2
b10 3
b10 $
b10 +
b10 "
b10 )
b10 ,
b10 /
b10 0
1%
#320
0%
#330
b100 .
b110000 !
b110000 (
b110000 2
b11 3
b11 $
b11 +
b11 "
b11 )
b11 ,
b11 /
b11 0
1%
#340
0%
#350
b101 .
b11001 !
b11001 (
b11001 2
b100 3
b100 $
b100 +
b100 "
b100 )
b100 ,
b100 /
b100 0
1%
#360
0%
#370
b110 .
b10010 !
b10010 (
b10010 2
b101 3
b101 $
b101 +
b101 "
b101 )
b101 ,
b101 /
b101 0
1%
#380
0%
#390
b111 .
b10 !
b10 (
b10 2
b110 3
b110 $
b110 +
b110 "
b110 )
b110 ,
b110 /
b110 0
1%
#400
0%
#410
b1000 .
b1111000 !
b1111000 (
b1111000 2
b111 3
b111 $
b111 +
b111 "
b111 )
b111 ,
b111 /
b111 0
1%
#420
0%
#430
b1001 .
b0 !
b0 (
b0 2
b1000 3
b1000 $
b1000 +
b1000 "
b1000 )
b1000 ,
b1000 /
b1000 0
1%
#440
0%
#450
b1010 .
b10000 !
b10000 (
b10000 2
b1001 3
b1001 $
b1001 +
b1001 "
b1001 )
b1001 ,
b1001 /
b1001 0
1%
#460
0%
#470
b1011 .
b1111001 #
b1111001 *
b1111001 1
b1000000 !
b1000000 (
b1000000 2
b1 4
b0 3
b1010 $
b1010 +
b1010 "
b1010 )
b1010 ,
b1010 /
b1010 0
1%
#480
0%
#490
b0 .
b1111001 !
b1111001 (
b1111001 2
b1 3
1-
b1011 $
b1011 +
b1011 "
b1011 )
b1011 ,
b1011 /
b1011 0
1%
#500
0%
#510
b1 .
b1000000 #
b1000000 *
b1000000 1
b1000000 !
b1000000 (
b1000000 2
b0 4
b0 3
0-
b0 $
b0 +
b0 "
b0 )
b0 ,
b0 /
b0 0
1%
#520
0%
#530
b10 .
b1111001 !
b1111001 (
b1111001 2
b1 3
b1 $
b1 +
b1 "
b1 )
b1 ,
b1 /
b1 0
1%
#540
0%
#550
b11 .
b100100 !
b100100 (
b100100 2
b10 3
b10 $
b10 +
b10 "
b10 )
b10 ,
b10 /
b10 0
1%
#560
0%
#570
b100 .
b110000 !
b110000 (
b110000 2
b11 3
b11 $
b11 +
b11 "
b11 )
b11 ,
b11 /
b11 0
1%
#580
0%
#590
b101 .
b11001 !
b11001 (
b11001 2
b100 3
b100 $
b100 +
b100 "
b100 )
b100 ,
b100 /
b100 0
1%
#600
0%
#610
b110 .
b10010 !
b10010 (
b10010 2
b101 3
b101 $
b101 +
b101 "
b101 )
b101 ,
b101 /
b101 0
1%
#620
0%
#630
b111 .
b10 !
b10 (
b10 2
b110 3
b110 $
b110 +
b110 "
b110 )
b110 ,
b110 /
b110 0
1%
#640
0%
#650
b1000 .
b1111000 !
b1111000 (
b1111000 2
b111 3
b111 $
b111 +
b111 "
b111 )
b111 ,
b111 /
b111 0
1%
#660
0%
#670
b1001 .
b0 !
b0 (
b0 2
b1000 3
b1000 $
b1000 +
b1000 "
b1000 )
b1000 ,
b1000 /
b1000 0
1%
#680
0%
#690
b1010 .
b10000 !
b10000 (
b10000 2
b1001 3
b1001 $
b1001 +
b1001 "
b1001 )
b1001 ,
b1001 /
b1001 0
1%
#700
0%
#710
b1011 .
b1111001 #
b1111001 *
b1111001 1
b1000000 !
b1000000 (
b1000000 2
b1 4
b0 3
b1010 $
b1010 +
b1010 "
b1010 )
b1010 ,
b1010 /
b1010 0
1%
#720
0%
#730
b0 .
b1111001 !
b1111001 (
b1111001 2
b1 3
1-
b1011 $
b1011 +
b1011 "
b1011 )
b1011 ,
b1011 /
b1011 0
1%
#740
0%
#750
b1 .
b1000000 #
b1000000 *
b1000000 1
b1000000 !
b1000000 (
b1000000 2
b0 4
b0 3
0-
b0 $
b0 +
b0 "
b0 )
b0 ,
b0 /
b0 0
1%
#760
0%
#770
b10 .
b1111001 !
b1111001 (
b1111001 2
b1 3
b1 $
b1 +
b1 "
b1 )
b1 ,
b1 /
b1 0
1%
#780
0%
#790
b11 .
b100100 !
b100100 (
b100100 2
b10 3
b10 $
b10 +
b10 "
b10 )
b10 ,
b10 /
b10 0
1%
#800
0%
#810
b100 .
b110000 !
b110000 (
b110000 2
b11 3
b11 $
b11 +
b11 "
b11 )
b11 ,
b11 /
b11 0
1%
#820
0%
#830
b101 .
b11001 !
b11001 (
b11001 2
b100 3
b100 $
b100 +
b100 "
b100 )
b100 ,
b100 /
b100 0
1%
#840
0%
#850
b110 .
b10010 !
b10010 (
b10010 2
b101 3
b101 $
b101 +
b101 "
b101 )
b101 ,
b101 /
b101 0
1%
#860
0%
#870
b111 .
b10 !
b10 (
b10 2
b110 3
b110 $
b110 +
b110 "
b110 )
b110 ,
b110 /
b110 0
1%
#880
0%
#890
b1000 .
b1111000 !
b1111000 (
b1111000 2
b111 3
b111 $
b111 +
b111 "
b111 )
b111 ,
b111 /
b111 0
1%
#900
0%
#910
b1001 .
b0 !
b0 (
b0 2
b1000 3
b1000 $
b1000 +
b1000 "
b1000 )
b1000 ,
b1000 /
b1000 0
1%
#920
0%
#930
b1010 .
b10000 !
b10000 (
b10000 2
b1001 3
b1001 $
b1001 +
b1001 "
b1001 )
b1001 ,
b1001 /
b1001 0
1%
#940
0%
#950
b1011 .
b1111001 #
b1111001 *
b1111001 1
b1000000 !
b1000000 (
b1000000 2
b1 4
b0 3
b1010 $
b1010 +
b1010 "
b1010 )
b1010 ,
b1010 /
b1010 0
1%
#960
0%
#970
b0 .
b1111001 !
b1111001 (
b1111001 2
b1 3
1-
b1011 $
b1011 +
b1011 "
b1011 )
b1011 ,
b1011 /
b1011 0
1%
#980
0%
#990
b1 .
b1000000 #
b1000000 *
b1000000 1
b1000000 !
b1000000 (
b1000000 2
b0 4
b0 3
0-
b0 $
b0 +
b0 "
b0 )
b0 ,
b0 /
b0 0
1%
#1000
0%
#1010
b10 .
b1111001 !
b1111001 (
b1111001 2
b1 3
b1 $
b1 +
b1 "
b1 )
b1 ,
b1 /
b1 0
1%
#1020
0%
#1030
b11 .
b100100 !
b100100 (
b100100 2
b10 3
b10 $
b10 +
b10 "
b10 )
b10 ,
b10 /
b10 0
1%
#1040
0%
#1050
b100 .
b110000 !
b110000 (
b110000 2
b11 3
b11 $
b11 +
b11 "
b11 )
b11 ,
b11 /
b11 0
1%
#1060
0%
#1070
b101 .
b11001 !
b11001 (
b11001 2
b100 3
b100 $
b100 +
b100 "
b100 )
b100 ,
b100 /
b100 0
1%
#1080
0%
#1090
b110 .
b10010 !
b10010 (
b10010 2
b101 3
b101 $
b101 +
b101 "
b101 )
b101 ,
b101 /
b101 0
1%
#1100
0%
#1110
b111 .
b10 !
b10 (
b10 2
b110 3
b110 $
b110 +
b110 "
b110 )
b110 ,
b110 /
b110 0
1%
#1120
0%
#1130
b1000 .
b1111000 !
b1111000 (
b1111000 2
b111 3
b111 $
b111 +
b111 "
b111 )
b111 ,
b111 /
b111 0
1%
#1140
0%
#1150
b1001 .
b0 !
b0 (
b0 2
b1000 3
b1000 $
b1000 +
b1000 "
b1000 )
b1000 ,
b1000 /
b1000 0
1%
#1160
0%
#1170
b1010 .
b10000 !
b10000 (
b10000 2
b1001 3
b1001 $
b1001 +
b1001 "
b1001 )
b1001 ,
b1001 /
b1001 0
1%
#1180
0%
#1190
b1011 .
b1111001 #
b1111001 *
b1111001 1
b1000000 !
b1000000 (
b1000000 2
b1 4
b0 3
b1010 $
b1010 +
b1010 "
b1010 )
b1010 ,
b1010 /
b1010 0
1%
#1200
0%
#1210
b0 .
b1111001 !
b1111001 (
b1111001 2
b1 3
1-
b1011 $
b1011 +
b1011 "
b1011 )
b1011 ,
b1011 /
b1011 0
1%
#1220
0%
#1230
b1 .
b1000000 #
b1000000 *
b1000000 1
b1000000 !
b1000000 (
b1000000 2
b0 4
b0 3
0-
b0 $
b0 +
b0 "
b0 )
b0 ,
b0 /
b0 0
1%
#1240
0%
#1250
b10 .
b1111001 !
b1111001 (
b1111001 2
b1 3
b1 $
b1 +
b1 "
b1 )
b1 ,
b1 /
b1 0
1%
#1260
0%
#1270
b11 .
b100100 !
b100100 (
b100100 2
b10 3
b10 $
b10 +
b10 "
b10 )
b10 ,
b10 /
b10 0
1%
#1280
0%
#1290
b100 .
b110000 !
b110000 (
b110000 2
b11 3
b11 $
b11 +
b11 "
b11 )
b11 ,
b11 /
b11 0
1%
#1300
0%
#1310
b101 .
b11001 !
b11001 (
b11001 2
b100 3
b100 $
b100 +
b100 "
b100 )
b100 ,
b100 /
b100 0
1%
#1320
0%
#1330
b110 .
b10010 !
b10010 (
b10010 2
b101 3
b101 $
b101 +
b101 "
b101 )
b101 ,
b101 /
b101 0
1%
#1340
0%
#1350
b111 .
b10 !
b10 (
b10 2
b110 3
b110 $
b110 +
b110 "
b110 )
b110 ,
b110 /
b110 0
1%
#1360
0%
#1370
b1000 .
b1111000 !
b1111000 (
b1111000 2
b111 3
b111 $
b111 +
b111 "
b111 )
b111 ,
b111 /
b111 0
1%
#1380
0%
#1390
b1001 .
b0 !
b0 (
b0 2
b1000 3
b1000 $
b1000 +
b1000 "
b1000 )
b1000 ,
b1000 /
b1000 0
1%
#1400
0%
#1410
b1010 .
b10000 !
b10000 (
b10000 2
b1001 3
b1001 $
b1001 +
b1001 "
b1001 )
b1001 ,
b1001 /
b1001 0
1%
#1420
0%
#1430
b1011 .
b1111001 #
b1111001 *
b1111001 1
b1000000 !
b1000000 (
b1000000 2
b1 4
b0 3
b1010 $
b1010 +
b1010 "
b1010 )
b1010 ,
b1010 /
b1010 0
1%
#1440
0%
#1450
b0 .
b1111001 !
b1111001 (
b1111001 2
b1 3
1-
b1011 $
b1011 +
b1011 "
b1011 )
b1011 ,
b1011 /
b1011 0
1%
#1460
0%
#1470
b1 .
b1000000 #
b1000000 *
b1000000 1
b1000000 !
b1000000 (
b1000000 2
b0 4
b0 3
0-
b0 $
b0 +
b0 "
b0 )
b0 ,
b0 /
b0 0
1%
#1480
0%
#1490
b10 .
b1111001 !
b1111001 (
b1111001 2
b1 3
b1 $
b1 +
b1 "
b1 )
b1 ,
b1 /
b1 0
1%
#1500
0%
#1510
b11 .
b100100 !
b100100 (
b100100 2
b10 3
b10 $
b10 +
b10 "
b10 )
b10 ,
b10 /
b10 0
1%
#1520
0%
#1530
b100 .
b110000 !
b110000 (
b110000 2
b11 3
b11 $
b11 +
b11 "
b11 )
b11 ,
b11 /
b11 0
1%
#1540
0%
#1550
b101 .
b11001 !
b11001 (
b11001 2
b100 3
b100 $
b100 +
b100 "
b100 )
b100 ,
b100 /
b100 0
1%
#1560
0%
#1570
b110 .
b10010 !
b10010 (
b10010 2
b101 3
b101 $
b101 +
b101 "
b101 )
b101 ,
b101 /
b101 0
1%
#1580
0%
#1590
b111 .
b10 !
b10 (
b10 2
b110 3
b110 $
b110 +
b110 "
b110 )
b110 ,
b110 /
b110 0
1%
#1600
0%
#1610
b1000 .
b1111000 !
b1111000 (
b1111000 2
b111 3
b111 $
b111 +
b111 "
b111 )
b111 ,
b111 /
b111 0
1%
#1620
0%
#1630
b1001 .
b0 !
b0 (
b0 2
b1000 3
b1000 $
b1000 +
b1000 "
b1000 )
b1000 ,
b1000 /
b1000 0
1%
#1640
0%
#1650
b1010 .
b10000 !
b10000 (
b10000 2
b1001 3
b1001 $
b1001 +
b1001 "
b1001 )
b1001 ,
b1001 /
b1001 0
1%
#1660
0%
#1670
b1011 .
b1111001 #
b1111001 *
b1111001 1
b1000000 !
b1000000 (
b1000000 2
b1 4
b0 3
b1010 $
b1010 +
b1010 "
b1010 )
b1010 ,
b1010 /
b1010 0
1%
#1680
0%
#1690
b0 .
b1111001 !
b1111001 (
b1111001 2
b1 3
1-
b1011 $
b1011 +
b1011 "
b1011 )
b1011 ,
b1011 /
b1011 0
1%
#1700
0%
#1710
b1 .
b1000000 #
b1000000 *
b1000000 1
b1000000 !
b1000000 (
b1000000 2
b0 4
b0 3
0-
b0 $
b0 +
b0 "
b0 )
b0 ,
b0 /
b0 0
1%
#1720
0%
#1730
b10 .
b1111001 !
b1111001 (
b1111001 2
b1 3
b1 $
b1 +
b1 "
b1 )
b1 ,
b1 /
b1 0
1%
#1740
0%
#1750
b11 .
b100100 !
b100100 (
b100100 2
b10 3
b10 $
b10 +
b10 "
b10 )
b10 ,
b10 /
b10 0
1%
#1760
0%
#1770
b100 .
b110000 !
b110000 (
b110000 2
b11 3
b11 $
b11 +
b11 "
b11 )
b11 ,
b11 /
b11 0
1%
#1780
0%
#1790
b101 .
b11001 !
b11001 (
b11001 2
b100 3
b100 $
b100 +
b100 "
b100 )
b100 ,
b100 /
b100 0
1%
#1800
0%
#1810
b110 .
b10010 !
b10010 (
b10010 2
b101 3
b101 $
b101 +
b101 "
b101 )
b101 ,
b101 /
b101 0
1%
#1820
0%
#1830
b111 .
b10 !
b10 (
b10 2
b110 3
b110 $
b110 +
b110 "
b110 )
b110 ,
b110 /
b110 0
1%
#1840
0%
#1850
b1000 .
b1111000 !
b1111000 (
b1111000 2
b111 3
b111 $
b111 +
b111 "
b111 )
b111 ,
b111 /
b111 0
1%
#1860
0%
#1870
b1001 .
b0 !
b0 (
b0 2
b1000 3
b1000 $
b1000 +
b1000 "
b1000 )
b1000 ,
b1000 /
b1000 0
1%
#1880
0%
#1890
b1010 .
b10000 !
b10000 (
b10000 2
b1001 3
b1001 $
b1001 +
b1001 "
b1001 )
b1001 ,
b1001 /
b1001 0
1%
#1900
0%
#1910
b1011 .
b1111001 #
b1111001 *
b1111001 1
b1000000 !
b1000000 (
b1000000 2
b1 4
b0 3
b1010 $
b1010 +
b1010 "
b1010 )
b1010 ,
b1010 /
b1010 0
1%
#1920
0%
#1930
b0 .
b1111001 !
b1111001 (
b1111001 2
b1 3
1-
b1011 $
b1011 +
b1011 "
b1011 )
b1011 ,
b1011 /
b1011 0
1%
#1940
0%
#1950
b1 .
b1000000 #
b1000000 *
b1000000 1
b1000000 !
b1000000 (
b1000000 2
b0 4
b0 3
0-
b0 $
b0 +
b0 "
b0 )
b0 ,
b0 /
b0 0
1%
#1960
0%
#1970
b10 .
b1111001 !
b1111001 (
b1111001 2
b1 3
b1 $
b1 +
b1 "
b1 )
b1 ,
b1 /
b1 0
1%
#1980
0%
#1990
b11 .
b100100 !
b100100 (
b100100 2
b10 3
b10 $
b10 +
b10 "
b10 )
b10 ,
b10 /
b10 0
1%
#2000
0%
#2010
b100 .
b110000 !
b110000 (
b110000 2
b11 3
b11 $
b11 +
b11 "
b11 )
b11 ,
b11 /
b11 0
1%
#2020
0%
#2030
b101 .
b11001 !
b11001 (
b11001 2
b100 3
b100 $
b100 +
b100 "
b100 )
b100 ,
b100 /
b100 0
1%
#2040
0%
#2050
b110 .
b10010 !
b10010 (
b10010 2
b101 3
b101 $
b101 +
b101 "
b101 )
b101 ,
b101 /
b101 0
1%
#2060
0%
#2070
b111 .
b10 !
b10 (
b10 2
b110 3
b110 $
b110 +
b110 "
b110 )
b110 ,
b110 /
b110 0
1%
#2080
0%
#2090
b1000 .
b1111000 !
b1111000 (
b1111000 2
b111 3
b111 $
b111 +
b111 "
b111 )
b111 ,
b111 /
b111 0
1%
#2100
0%
#2110
b1001 .
b0 !
b0 (
b0 2
b1000 3
b1000 $
b1000 +
b1000 "
b1000 )
b1000 ,
b1000 /
b1000 0
1%
#2120
0%
#2130
b1010 .
b10000 !
b10000 (
b10000 2
b1001 3
b1001 $
b1001 +
b1001 "
b1001 )
b1001 ,
b1001 /
b1001 0
1%
#2140
0%
#2150
b1011 .
b1111001 #
b1111001 *
b1111001 1
b1000000 !
b1000000 (
b1000000 2
b1 4
b0 3
b1010 $
b1010 +
b1010 "
b1010 )
b1010 ,
b1010 /
b1010 0
1%
#2160
0%
#2170
b0 .
b1111001 !
b1111001 (
b1111001 2
b1 3
1-
b1011 $
b1011 +
b1011 "
b1011 )
b1011 ,
b1011 /
b1011 0
1%
#2180
0%
#2190
b1 .
b1000000 #
b1000000 *
b1000000 1
b1000000 !
b1000000 (
b1000000 2
b0 4
b0 3
0-
b0 $
b0 +
b0 "
b0 )
b0 ,
b0 /
b0 0
1%
#2200
0%
#2210
b10 .
b1111001 !
b1111001 (
b1111001 2
b1 3
b1 $
b1 +
b1 "
b1 )
b1 ,
b1 /
b1 0
1%
#2220
0%
#2230
b11 .
b100100 !
b100100 (
b100100 2
b10 3
b10 $
b10 +
b10 "
b10 )
b10 ,
b10 /
b10 0
1%
#2240
0%
#2250
b100 .
b110000 !
b110000 (
b110000 2
b11 3
b11 $
b11 +
b11 "
b11 )
b11 ,
b11 /
b11 0
1%
#2260
0%
#2270
b101 .
b11001 !
b11001 (
b11001 2
b100 3
b100 $
b100 +
b100 "
b100 )
b100 ,
b100 /
b100 0
1%
#2280
0%
#2290
b110 .
b10010 !
b10010 (
b10010 2
b101 3
b101 $
b101 +
b101 "
b101 )
b101 ,
b101 /
b101 0
1%
#2300
0%
#2310
b111 .
b10 !
b10 (
b10 2
b110 3
b110 $
b110 +
b110 "
b110 )
b110 ,
b110 /
b110 0
1%
#2320
0%
#2330
b1000 .
b1111000 !
b1111000 (
b1111000 2
b111 3
b111 $
b111 +
b111 "
b111 )
b111 ,
b111 /
b111 0
1%
#2340
0%
#2350
b1001 .
b0 !
b0 (
b0 2
b1000 3
b1000 $
b1000 +
b1000 "
b1000 )
b1000 ,
b1000 /
b1000 0
1%
#2360
0%
#2370
b1010 .
b10000 !
b10000 (
b10000 2
b1001 3
b1001 $
b1001 +
b1001 "
b1001 )
b1001 ,
b1001 /
b1001 0
1%
#2380
0%
#2390
b1011 .
b1111001 #
b1111001 *
b1111001 1
b1000000 !
b1000000 (
b1000000 2
b1 4
b0 3
b1010 $
b1010 +
b1010 "
b1010 )
b1010 ,
b1010 /
b1010 0
1%
#2400
0%
#2410
b0 .
b1111001 !
b1111001 (
b1111001 2
b1 3
1-
b1011 $
b1011 +
b1011 "
b1011 )
b1011 ,
b1011 /
b1011 0
1%
#2420
0%
#2430
b1 .
b1000000 #
b1000000 *
b1000000 1
b1000000 !
b1000000 (
b1000000 2
b0 4
b0 3
0-
b0 $
b0 +
b0 "
b0 )
b0 ,
b0 /
b0 0
1%
#2440
0%
#2450
b10 .
b1111001 !
b1111001 (
b1111001 2
b1 3
b1 $
b1 +
b1 "
b1 )
b1 ,
b1 /
b1 0
1%
#2460
0%
#2470
b11 .
b100100 !
b100100 (
b100100 2
b10 3
b10 $
b10 +
b10 "
b10 )
b10 ,
b10 /
b10 0
1%
#2480
0%
#2490
b100 .
b110000 !
b110000 (
b110000 2
b11 3
b11 $
b11 +
b11 "
b11 )
b11 ,
b11 /
b11 0
1%
#2500
0%
#2510
b101 .
b11001 !
b11001 (
b11001 2
b100 3
b100 $
b100 +
b100 "
b100 )
b100 ,
b100 /
b100 0
1%
#2520
0%
#2530
b110 .
b10010 !
b10010 (
b10010 2
b101 3
b101 $
b101 +
b101 "
b101 )
b101 ,
b101 /
b101 0
1%
#2540
0%
#2550
b111 .
b10 !
b10 (
b10 2
b110 3
b110 $
b110 +
b110 "
b110 )
b110 ,
b110 /
b110 0
1%
#2560
0%
#2570
b1000 .
b1111000 !
b1111000 (
b1111000 2
b111 3
b111 $
b111 +
b111 "
b111 )
b111 ,
b111 /
b111 0
1%
#2580
0%
#2590
b1001 .
b0 !
b0 (
b0 2
b1000 3
b1000 $
b1000 +
b1000 "
b1000 )
b1000 ,
b1000 /
b1000 0
1%
#2600
0%
#2610
b1010 .
b10000 !
b10000 (
b10000 2
b1001 3
b1001 $
b1001 +
b1001 "
b1001 )
b1001 ,
b1001 /
b1001 0
1%
#2620
0%
#2630
b1011 .
b1111001 #
b1111001 *
b1111001 1
b1000000 !
b1000000 (
b1000000 2
b1 4
b0 3
b1010 $
b1010 +
b1010 "
b1010 )
b1010 ,
b1010 /
b1010 0
1%
#2640
0%
#2650
b0 .
b1111001 !
b1111001 (
b1111001 2
b1 3
1-
b1011 $
b1011 +
b1011 "
b1011 )
b1011 ,
b1011 /
b1011 0
1%
#2660
0%
#2670
b1 .
b1000000 #
b1000000 *
b1000000 1
b1000000 !
b1000000 (
b1000000 2
b0 4
b0 3
0-
b0 $
b0 +
b0 "
b0 )
b0 ,
b0 /
b0 0
1%
#2680
0%
#2690
b10 .
b1111001 !
b1111001 (
b1111001 2
b1 3
b1 $
b1 +
b1 "
b1 )
b1 ,
b1 /
b1 0
1%
#2700
0%
#2710
b11 .
b100100 !
b100100 (
b100100 2
b10 3
b10 $
b10 +
b10 "
b10 )
b10 ,
b10 /
b10 0
1%
#2720
0%
#2730
b100 .
b110000 !
b110000 (
b110000 2
b11 3
b11 $
b11 +
b11 "
b11 )
b11 ,
b11 /
b11 0
1%
#2740
0%
#2750
b101 .
b11001 !
b11001 (
b11001 2
b100 3
b100 $
b100 +
b100 "
b100 )
b100 ,
b100 /
b100 0
1%
#2760
0%
#2770
b110 .
b10010 !
b10010 (
b10010 2
b101 3
b101 $
b101 +
b101 "
b101 )
b101 ,
b101 /
b101 0
1%
#2780
0%
#2790
b111 .
b10 !
b10 (
b10 2
b110 3
b110 $
b110 +
b110 "
b110 )
b110 ,
b110 /
b110 0
1%
#2800
0%
#2810
b1000 .
b1111000 !
b1111000 (
b1111000 2
b111 3
b111 $
b111 +
b111 "
b111 )
b111 ,
b111 /
b111 0
1%
#2820
0%
#2830
b1001 .
b0 !
b0 (
b0 2
b1000 3
b1000 $
b1000 +
b1000 "
b1000 )
b1000 ,
b1000 /
b1000 0
1%
#2840
0%
#2850
b1010 .
b10000 !
b10000 (
b10000 2
b1001 3
b1001 $
b1001 +
b1001 "
b1001 )
b1001 ,
b1001 /
b1001 0
1%
#2860
0%
#2870
b1011 .
b1111001 #
b1111001 *
b1111001 1
b1000000 !
b1000000 (
b1000000 2
b1 4
b0 3
b1010 $
b1010 +
b1010 "
b1010 )
b1010 ,
b1010 /
b1010 0
1%
#2880
0%
#2890
b0 .
b1111001 !
b1111001 (
b1111001 2
b1 3
1-
b1011 $
b1011 +
b1011 "
b1011 )
b1011 ,
b1011 /
b1011 0
1%
#2900
0%
#2910
b1 .
b1000000 #
b1000000 *
b1000000 1
b1000000 !
b1000000 (
b1000000 2
b0 4
b0 3
0-
b0 $
b0 +
b0 "
b0 )
b0 ,
b0 /
b0 0
1%
#2920
0%
#2930
b10 .
b1111001 !
b1111001 (
b1111001 2
b1 3
b1 $
b1 +
b1 "
b1 )
b1 ,
b1 /
b1 0
1%
#2940
0%
#2950
b11 .
b100100 !
b100100 (
b100100 2
b10 3
b10 $
b10 +
b10 "
b10 )
b10 ,
b10 /
b10 0
1%
#2960
0%
#2970
b100 .
b110000 !
b110000 (
b110000 2
b11 3
b11 $
b11 +
b11 "
b11 )
b11 ,
b11 /
b11 0
1%
#2980
0%
#2990
b101 .
b11001 !
b11001 (
b11001 2
b100 3
b100 $
b100 +
b100 "
b100 )
b100 ,
b100 /
b100 0
1%
#3000
0%
